gyk230621/ML.py
gyk230621/__init__.py
gyk230621-0.0.1.dist-info/LICENSE
gyk230621-0.0.1.dist-info/METADATA
gyk230621-0.0.1.dist-info/WHEEL
gyk230621-0.0.1.dist-info/top_level.txt
gyk230621-0.0.1.dist-info/RECORD
